watchmen/__init__.py
watchmen/client.py
watchmen/listener.py
watchmen/reminder.py
watchmen/server.py
watchmen/wait.py
watchmen/templates/index.html
watchmen/templates/old_index.html
gpu_watchmen-0.4.0.dist-info/LICENSE
gpu_watchmen-0.4.0.dist-info/METADATA
gpu_watchmen-0.4.0.dist-info/WHEEL
gpu_watchmen-0.4.0.dist-info/top_level.txt
gpu_watchmen-0.4.0.dist-info/RECORD
