Metadata-Version: 2.2
Name: gpu-watchmen
Version: 0.4.0
Summary: watchmen for GPU scheduling
Home-page: https://github.com/Spico197/watchmen
Author: Tong Zhu
Author-email: tzhu1997@outlook.com
Classifier: Programming Language :: Python :: 3
Classifier: License :: OSI Approved :: MIT License
Classifier: Operating System :: POSIX :: Linux
Requires-Python: >=3.6
License-File: LICENSE
Requires-Dist: apscheduler>=3.6.3
Requires-Dist: flask>=1.1.2
Requires-Dist: gpustat>=0.6.0
Requires-Dist: pydantic>=1.7.1
Requires-Dist: requests>=2.24.0
Dynamic: author
Dynamic: author-email
Dynamic: classifier
Dynamic: description
Dynamic: description-content-type
Dynamic: home-page
Dynamic: requires-dist
Dynamic: requires-python
Dynamic: summary
